{
  "iteration": 20,
  "generation": 20,
  "best_win_rate": 55.96,
  "current_config": {
    "vol_multiplier": 1.07,
    "displacement_multiplier": 1.51,
    "swing_lookback": 11,
    "mss_swing_len": 4,
    "max_bars_after_sweep": 11,
    "wins": 102,
    "losses": 97,
    "total_pnl": 8475.64,
    "win_rate": 51.26,
    "generation": 21,
    "parent_config": "gen20",
    "failure_reasons": []
  },
  "winning_configs_count": 3,
  "failure_patterns": {
    "low_confidence": 189,
    "small_move_chop": 108
  }
}